README.md
setup.cfg
setup.py
bluetooth_battery/__init__.py
bluetooth_battery/bluetooth_battery.py
bluetooth_battery.egg-info/PKG-INFO
bluetooth_battery.egg-info/SOURCES.txt
bluetooth_battery.egg-info/dependency_links.txt
bluetooth_battery.egg-info/entry_points.txt
bluetooth_battery.egg-info/requires.txt
bluetooth_battery.egg-info/top_level.txt