Metadata-Version: 2.1
Name: bluetooth-battery
Version: 1.2.0
Summary: A python script to get battery level from Bluetooth headsets
Home-page: https://github.com/TheWeirdDev/Bluetooth_Headset_Battery_Level
Author: TheWeirdDev
Author-email: alireza6677@gmail.com
License: GPL-3.0
Download-URL: https://github.com/TheWeirdDev/Bluetooth_Headset_Battery_Level/archive/v1.2.0.zip
Keywords: bluetooth,bluetooth-headsets,bluetooth-devices,battery-level,battery-percentage,battery,headset,linux,socket,python,at-command,bluetooth-socket,bluetooth-speaker,bluez,headphones,bluetooth-headphones,python-script
Platform: UNKNOWN
Classifier: Development Status :: 5 - Production/Stable
Classifier: Intended Audience :: End Users/Desktop
Classifier: Topic :: Utilities
Classifier: License :: OSI Approved :: GNU General Public License v3 or later (GPLv3+)
Classifier: Programming Language :: Python :: 3.6
Classifier: Programming Language :: Python :: 3.7
Classifier: Programming Language :: Python :: 3.8
Classifier: Programming Language :: Python :: 3.9
Classifier: Programming Language :: Python :: 3 :: Only
